halerium_utilities/__init__.py
halerium_utilities/version.py
halerium_utilities/applications/__init__.py
halerium_utilities/applications/meeting_analyzer/__init__.py
halerium_utilities/applications/meeting_analyzer/app.py
halerium_utilities/applications/meeting_analyzer/frontend/static/font/ic_regular_alt.otf
halerium_utilities/applications/meeting_analyzer/frontend/static/font/ic_semibold_alt.otf
halerium_utilities/applications/meeting_analyzer/frontend/static/img/hal.png
halerium_utilities/applications/meeting_analyzer/frontend/static/img/icon-record-black.svg
halerium_utilities/applications/meeting_analyzer/frontend/static/img/icon-record-red.svg
halerium_utilities/applications/meeting_analyzer/frontend/static/img/logo_halerium.svg
halerium_utilities/applications/meeting_analyzer/frontend/static/scripts/audio-devices-handler.js
halerium_utilities/applications/meeting_analyzer/frontend/static/scripts/audio-processor.js
halerium_utilities/applications/meeting_analyzer/frontend/static/scripts/audio-recorder.js
halerium_utilities/applications/meeting_analyzer/frontend/static/scripts/audio-visualizer.js
halerium_utilities/applications/meeting_analyzer/frontend/static/scripts/dropdown-component.js
halerium_utilities/applications/meeting_analyzer/frontend/static/scripts/mode-selector.js
halerium_utilities/applications/meeting_analyzer/frontend/static/scripts/transcribe-and-analyze-files.js
halerium_utilities/applications/meeting_analyzer/frontend/static/scripts/utils.js
halerium_utilities/applications/meeting_analyzer/frontend/static/scripts/websocket-handler.js
halerium_utilities/applications/meeting_analyzer/frontend/static/style/analysis.css
halerium_utilities/applications/meeting_analyzer/frontend/static/style/analysis.css.map
halerium_utilities/applications/meeting_analyzer/frontend/static/style/analysis.scss
halerium_utilities/applications/meeting_analyzer/frontend/static/style/dropdownComponent.css
halerium_utilities-2.30.1.dist-info/METADATA
halerium_utilities-2.30.1.dist-info/WHEEL
halerium_utilities-2.30.1.dist-info/entry_points.txt
halerium_utilities-2.30.1.dist-info/top_level.txt
halerium_utilities-2.30.1.dist-info/RECORD
