Metadata-Version: 2.4
Name: halerium_utilities
Version: 2.30.1
Summary: Halerium utilities is a Python package of utility functions for working on the Halerium platform.
Home-page: https://erium.de
Author: Erium GmbH
Author-email: info@erium.de
License: Apache 2.0
Project-URL: Documentation, https://erium.gitlab.io/halerium_utilities/
Requires-Dist: httpx<1,>0.23
Requires-Dist: pydantic<2.10,>2
Provides-Extra: test
Requires-Dist: pytest<8,>7; extra == "test"
Requires-Dist: pytest-cov<5,>3; extra == "test"
Requires-Dist: pytest-asyncio<0.24,>=0.23; extra == "test"
Requires-Dist: pytest-httpx<1,>=0.25.0; extra == "test"
Requires-Dist: numpy<2,>1.19; extra == "test"
Provides-Extra: polybot
Requires-Dist: fastapi~=0.109.0; extra == "polybot"
Requires-Dist: httpx<0.27,>=0.25.2; extra == "polybot"
Requires-Dist: jinja2~=3.1.2; extra == "polybot"
Requires-Dist: lameenc~=1.7.0; extra == "polybot"
Requires-Dist: python-multipart~=0.0.6; extra == "polybot"
Requires-Dist: uvicorn<0.28,>=0.25.0; extra == "polybot"
Requires-Dist: websockets~=12.0; extra == "polybot"
Provides-Extra: pdf
Requires-Dist: pillow~=10.3.0; extra == "pdf"
Requires-Dist: PyMuPDF~=1.24.5; extra == "pdf"
Requires-Dist: tabulate~=0.9.0; extra == "pdf"
Provides-Extra: jira
Requires-Dist: beautifulsoup4~=4.12.3; extra == "jira"
Requires-Dist: lxml~=5.2.2; extra == "jira"
Provides-Extra: meeting-analyzer
Requires-Dist: fastapi~=0.109.0; extra == "meeting-analyzer"
Requires-Dist: jinja2~=3.1.2; extra == "meeting-analyzer"
Requires-Dist: uvicorn<0.28,>=0.25.0; extra == "meeting-analyzer"
Requires-Dist: lameenc~=1.7.0; extra == "meeting-analyzer"
Provides-Extra: runner-functions
Requires-Dist: python-docx<2,>=1.1; extra == "runner-functions"
Requires-Dist: python-pptx<2,>=1.0; extra == "runner-functions"
Requires-Dist: jira<4,>=3.7; extra == "runner-functions"
Requires-Dist: selenium<5,>4.15; extra == "runner-functions"
Provides-Extra: all
Requires-Dist: tabulate~=0.9.0; extra == "all"
Requires-Dist: python-docx<2,>=1.1; extra == "all"
Requires-Dist: websockets~=12.0; extra == "all"
Requires-Dist: fastapi~=0.109.0; extra == "all"
Requires-Dist: PyMuPDF~=1.24.5; extra == "all"
Requires-Dist: lxml~=5.2.2; extra == "all"
Requires-Dist: beautifulsoup4~=4.12.3; extra == "all"
Requires-Dist: lameenc~=1.7.0; extra == "all"
Requires-Dist: python-pptx<2,>=1.0; extra == "all"
Requires-Dist: selenium<5,>4.15; extra == "all"
Requires-Dist: python-multipart~=0.0.6; extra == "all"
Requires-Dist: pillow~=10.3.0; extra == "all"
Requires-Dist: httpx<0.27,>=0.25.2; extra == "all"
Requires-Dist: uvicorn<0.28,>=0.25.0; extra == "all"
Requires-Dist: jira<4,>=3.7; extra == "all"
Requires-Dist: jinja2~=3.1.2; extra == "all"
Dynamic: author
Dynamic: author-email
Dynamic: home-page
Dynamic: license
Dynamic: project-url
Dynamic: provides-extra
Dynamic: requires-dist
Dynamic: summary
